crstr/__init__.py
crstr/__main__.py
crstr-1.0.0.dist-info/LICENSE
crstr-1.0.0.dist-info/METADATA
crstr-1.0.0.dist-info/WHEEL
crstr-1.0.0.dist-info/top_level.txt
crstr-1.0.0.dist-info/RECORD
