Metadata-Version: 2.1
Name: crstr
Version: 1.0.0
Summary: shell wrapper for rstr (https://pypi.org/project/rstr/)
Home-page: https://github.com/li-zyang/zTools/tree/master/crstr
Author: li-zyang
Author-email: K_AEIx@163.com
License: UNKNOWN
Platform: UNKNOWN
Classifier: Programming Language :: Python :: 3
Classifier: License :: OSI Approved :: MIT License
Classifier: Operating System :: OS Independent
Requires-Python: >=3.6
